odoo/addons/sale_order_partner_ref/LICENSE
odoo/addons/sale_order_partner_ref/README.rst
odoo/addons/sale_order_partner_ref/__init__.py
odoo/addons/sale_order_partner_ref/__manifest__.py
odoo/addons/sale_order_partner_ref/i18n/de_CH.po
odoo/addons/sale_order_partner_ref/images/screen.png
odoo/addons/sale_order_partner_ref/models/__init__.py
odoo/addons/sale_order_partner_ref/models/sale_order.py
odoo/addons/sale_order_partner_ref/static/description/icon.png
odoo/addons/sale_order_partner_ref/static/description/index.html
odoo/addons/sale_order_partner_ref/tests/TEST_INSTRUCTIONS.rst
odoo/addons/sale_order_partner_ref/views/sale_order.xml
odoo_addon_sale_order_partner_ref-18.0.1.0.0.dist-info/METADATA
odoo_addon_sale_order_partner_ref-18.0.1.0.0.dist-info/WHEEL
odoo_addon_sale_order_partner_ref-18.0.1.0.0.dist-info/top_level.txt
odoo_addon_sale_order_partner_ref-18.0.1.0.0.dist-info/RECORD
